rutube_studio_client/__init__.py
rutube_studio_client/client.py
rutube_studio_client/exceptions.py
rutube_studio_client/models.py
rutube_studio_client/utils.py
rutube_studio_client-0.1.0.dist-info/METADATA
rutube_studio_client-0.1.0.dist-info/WHEEL
rutube_studio_client-0.1.0.dist-info/RECORD
