Metadata-Version: 2.4
Name: rutube-studio-client
Version: 0.1.0
Summary: Async wrapper for Rutube Studio API
Requires-Python: >=3.8
Requires-Dist: httpx
Requires-Dist: pydantic
Requires-Dist: yt-dlp
